{"name": "Amyra", "slug": "amyra", "boys": [], "girls": [{"year": 2008, "count": 5, "rank": 3860}, {"year": 2009, "count": 6, "rank": 3422}, {"year": 2010, "count": 3, "rank": 5707}, {"year": 2012, "count": 5, "rank": 4171}, {"year": 2014, "count": 6, "rank": 3514}, {"year": 2015, "count": 14, "rank": 1961}, {"year": 2016, "count": 14, "rank": 2008}, {"year": 2017, "count": 21, "rank": 1512}, {"year": 2018, "count": 38, "rank": 952}, {"year": 2019, "count": 56, "rank": 694}, {"year": 2020, "count": 44, "rank": 821}, {"year": 2021, "count": 47, "rank": 779}, {"year": 2022, "count": 91, "rank": 462}, {"year": 2023, "count": 86, "rank": 461}, {"year": 2024, "count": 119, "rank": 365}]}