{"name": "Arian", "slug": "arian", "boys": [{"year": 1996, "count": 4, "rank": 2357}, {"year": 1997, "count": 4, "rank": 2337}, {"year": 1998, "count": 9, "rank": 1367}, {"year": 1999, "count": 12, "rank": 1130}, {"year": 2000, "count": 4, "rank": 2501}, {"year": 2001, "count": 9, "rank": 1467}, {"year": 2002, "count": 14, "rank": 1128}, {"year": 2003, "count": 17, "rank": 1053}, {"year": 2004, "count": 21, "rank": 970}, {"year": 2005, "count": 23, "rank": 954}, {"year": 2006, "count": 18, "rank": 1168}, {"year": 2007, "count": 23, "rank": 1053}, {"year": 2008, "count": 29, "rank": 916}, {"year": 2009, "count": 38, "rank": 760}, {"year": 2010, "count": 29, "rank": 970}, {"year": 2011, "count": 33, "rank": 878}, {"year": 2012, "count": 41, "rank": 783}, {"year": 2013, "count": 27, "rank": 1024}, {"year": 2014, "count": 34, "rank": 866}, {"year": 2015, "count": 37, "rank": 833}, {"year": 2016, "count": 38, "rank": 833}, {"year": 2017, "count": 40, "rank": 806}, {"year": 2018, "count": 44, "rank": 749}, {"year": 2019, "count": 40, "rank": 787}, {"year": 2020, "count": 33, "rank": 878}, {"year": 2021, "count": 41, "rank": 790}, {"year": 2022, "count": 33, "rank": 925}, {"year": 2023, "count": 41, "rank": 791}, {"year": 2024, "count": 56, "rank": 664}], "girls": [{"year": 1996, "count": 3, "rank": 3795}, {"year": 1997, "count": 6, "rank": 2411}, {"year": 1998, "count": 4, "rank": 3142}, {"year": 2000, "count": 4, "rank": 3247}, {"year": 2003, "count": 5, "rank": 3099}, {"year": 2004, "count": 4, "rank": 3725}, {"year": 2006, "count": 5, "rank": 3548}, {"year": 2008, "count": 5, "rank": 3860}, {"year": 2009, "count": 3, "rank": 5556}, {"year": 2018, "count": 3, "rank": 5666}]}