{"name": "Aviraj", "slug": "aviraj", "boys": [{"year": 2002, "count": 3, "rank": 3225}, {"year": 2012, "count": 7, "rank": 2721}, {"year": 2013, "count": 7, "rank": 2660}, {"year": 2014, "count": 8, "rank": 2459}, {"year": 2015, "count": 3, "rank": 4747}, {"year": 2016, "count": 13, "rank": 1804}, {"year": 2017, "count": 13, "rank": 1812}, {"year": 2018, "count": 14, "rank": 1683}, {"year": 2019, "count": 12, "rank": 1869}, {"year": 2020, "count": 17, "rank": 1431}, {"year": 2021, "count": 30, "rank": 985}, {"year": 2022, "count": 12, "rank": 1879}, {"year": 2023, "count": 54, "rank": 651}, {"year": 2024, "count": 54, "rank": 678}], "girls": []}