{"name": "Carla", "slug": "carla", "boys": [], "girls": [{"year": 1996, "count": 230, "rank": 192}, {"year": 1997, "count": 230, "rank": 186}, {"year": 1998, "count": 198, "rank": 208}, {"year": 1999, "count": 199, "rank": 210}, {"year": 2000, "count": 172, "rank": 238}, {"year": 2001, "count": 190, "rank": 208}, {"year": 2002, "count": 132, "rank": 288}, {"year": 2003, "count": 127, "rank": 310}, {"year": 2004, "count": 129, "rank": 313}, {"year": 2005, "count": 116, "rank": 345}, {"year": 2006, "count": 111, "rank": 378}, {"year": 2007, "count": 115, "rank": 369}, {"year": 2008, "count": 132, "rank": 341}, {"year": 2009, "count": 115, "rank": 374}, {"year": 2010, "count": 96, "rank": 438}, {"year": 2011, "count": 94, "rank": 449}, {"year": 2012, "count": 61, "rank": 679}, {"year": 2013, "count": 73, "rank": 561}, {"year": 2014, "count": 60, "rank": 663}, {"year": 2015, "count": 62, "rank": 656}, {"year": 2016, "count": 51, "rank": 768}, {"year": 2017, "count": 70, "rank": 604}, {"year": 2018, "count": 74, "rank": 560}, {"year": 2019, "count": 79, "rank": 513}, {"year": 2020, "count": 62, "rank": 617}, {"year": 2021, "count": 75, "rank": 537}, {"year": 2022, "count": 72, "rank": 541}, {"year": 2023, "count": 66, "rank": 583}, {"year": 2024, "count": 61, "rank": 638}]}