{"name": "Duncan", "slug": "duncan", "boys": [{"year": 1996, "count": 139, "rank": 220}, {"year": 1997, "count": 93, "rank": 289}, {"year": 1998, "count": 88, "rank": 298}, {"year": 1999, "count": 68, "rank": 349}, {"year": 2000, "count": 57, "rank": 392}, {"year": 2001, "count": 43, "rank": 482}, {"year": 2002, "count": 60, "rank": 392}, {"year": 2003, "count": 49, "rank": 490}, {"year": 2004, "count": 58, "rank": 459}, {"year": 2005, "count": 56, "rank": 493}, {"year": 2006, "count": 48, "rank": 596}, {"year": 2007, "count": 46, "rank": 631}, {"year": 2008, "count": 51, "rank": 613}, {"year": 2009, "count": 32, "rank": 868}, {"year": 2010, "count": 29, "rank": 970}, {"year": 2011, "count": 39, "rank": 781}, {"year": 2012, "count": 20, "rank": 1270}, {"year": 2013, "count": 33, "rank": 882}, {"year": 2014, "count": 21, "rank": 1223}, {"year": 2015, "count": 17, "rank": 1442}, {"year": 2016, "count": 26, "rank": 1081}, {"year": 2017, "count": 28, "rank": 1042}, {"year": 2018, "count": 21, "rank": 1235}, {"year": 2019, "count": 14, "rank": 1655}, {"year": 2020, "count": 16, "rank": 1492}, {"year": 2021, "count": 13, "rank": 1782}, {"year": 2022, "count": 18, "rank": 1420}, {"year": 2023, "count": 23, "rank": 1207}, {"year": 2024, "count": 15, "rank": 1675}], "girls": []}