{"name": "El", "slug": "el", "boys": [{"year": 1997, "count": 5, "rank": 2022}, {"year": 2001, "count": 4, "rank": 2587}, {"year": 2007, "count": 3, "rank": 4333}, {"year": 2008, "count": 4, "rank": 3687}, {"year": 2009, "count": 6, "rank": 2837}, {"year": 2011, "count": 4, "rank": 3830}, {"year": 2014, "count": 3, "rank": 4632}, {"year": 2015, "count": 3, "rank": 4747}, {"year": 2016, "count": 3, "rank": 4810}, {"year": 2017, "count": 3, "rank": 4812}, {"year": 2021, "count": 6, "rank": 3017}, {"year": 2024, "count": 4, "rank": 4270}], "girls": [{"year": 2014, "count": 4, "rank": 4684}, {"year": 2024, "count": 4, "rank": 4843}]}