{"name": "Eljay", "slug": "eljay", "boys": [{"year": 2004, "count": 3, "rank": 3651}, {"year": 2006, "count": 3, "rank": 4052}, {"year": 2009, "count": 7, "rank": 2544}, {"year": 2012, "count": 7, "rank": 2721}, {"year": 2015, "count": 3, "rank": 4747}, {"year": 2016, "count": 5, "rank": 3478}, {"year": 2017, "count": 3, "rank": 4812}, {"year": 2018, "count": 3, "rank": 4749}, {"year": 2019, "count": 4, "rank": 3937}, {"year": 2021, "count": 5, "rank": 3451}, {"year": 2022, "count": 5, "rank": 3449}, {"year": 2024, "count": 3, "rank": 5119}], "girls": []}