{"name": "Elon", "slug": "elon", "boys": [{"year": 2008, "count": 3, "rank": 4432}, {"year": 2010, "count": 6, "rank": 2941}, {"year": 2013, "count": 3, "rank": 4685}, {"year": 2015, "count": 6, "rank": 3004}, {"year": 2016, "count": 9, "rank": 2335}, {"year": 2017, "count": 14, "rank": 1703}, {"year": 2018, "count": 18, "rank": 1382}, {"year": 2019, "count": 19, "rank": 1316}, {"year": 2020, "count": 16, "rank": 1492}, {"year": 2021, "count": 16, "rank": 1516}, {"year": 2022, "count": 22, "rank": 1224}, {"year": 2023, "count": 21, "rank": 1272}, {"year": 2024, "count": 30, "rank": 1000}], "girls": []}