{"name": "Freddy", "slug": "freddy", "boys": [{"year": 1996, "count": 25, "rank": 633}, {"year": 1997, "count": 22, "rank": 725}, {"year": 1998, "count": 19, "rank": 813}, {"year": 1999, "count": 23, "rank": 718}, {"year": 2000, "count": 28, "rank": 651}, {"year": 2001, "count": 42, "rank": 484}, {"year": 2002, "count": 31, "rank": 633}, {"year": 2003, "count": 64, "rank": 406}, {"year": 2004, "count": 97, "rank": 305}, {"year": 2005, "count": 112, "rank": 288}, {"year": 2006, "count": 137, "rank": 266}, {"year": 2007, "count": 151, "rank": 267}, {"year": 2008, "count": 138, "rank": 298}, {"year": 2009, "count": 197, "rank": 228}, {"year": 2010, "count": 214, "rank": 224}, {"year": 2011, "count": 188, "rank": 257}, {"year": 2012, "count": 212, "rank": 238}, {"year": 2013, "count": 210, "rank": 241}, {"year": 2014, "count": 285, "rank": 199}, {"year": 2015, "count": 254, "rank": 221}, {"year": 2016, "count": 245, "rank": 229}, {"year": 2017, "count": 244, "rank": 218}, {"year": 2018, "count": 204, "rank": 251}, {"year": 2019, "count": 197, "rank": 249}, {"year": 2020, "count": 172, "rank": 275}, {"year": 2021, "count": 161, "rank": 293}, {"year": 2022, "count": 144, "rank": 314}, {"year": 2023, "count": 161, "rank": 284}, {"year": 2024, "count": 137, "rank": 318}], "girls": []}