{"name": "Jon", "slug": "jon", "boys": [{"year": 1996, "count": 124, "rank": 239}, {"year": 1997, "count": 115, "rank": 254}, {"year": 1998, "count": 85, "rank": 304}, {"year": 1999, "count": 88, "rank": 306}, {"year": 2000, "count": 78, "rank": 329}, {"year": 2001, "count": 88, "rank": 309}, {"year": 2002, "count": 75, "rank": 338}, {"year": 2003, "count": 80, "rank": 340}, {"year": 2004, "count": 64, "rank": 431}, {"year": 2005, "count": 61, "rank": 461}, {"year": 2006, "count": 63, "rank": 485}, {"year": 2007, "count": 66, "rank": 492}, {"year": 2008, "count": 36, "rank": 789}, {"year": 2009, "count": 43, "rank": 696}, {"year": 2010, "count": 28, "rank": 996}, {"year": 2011, "count": 33, "rank": 878}, {"year": 2012, "count": 30, "rank": 962}, {"year": 2013, "count": 31, "rank": 931}, {"year": 2014, "count": 34, "rank": 866}, {"year": 2015, "count": 23, "rank": 1159}, {"year": 2016, "count": 27, "rank": 1050}, {"year": 2017, "count": 21, "rank": 1247}, {"year": 2018, "count": 23, "rank": 1158}, {"year": 2019, "count": 18, "rank": 1369}, {"year": 2020, "count": 20, "rank": 1273}, {"year": 2021, "count": 14, "rank": 1688}, {"year": 2022, "count": 9, "rank": 2320}, {"year": 2023, "count": 18, "rank": 1407}, {"year": 2024, "count": 14, "rank": 1758}], "girls": []}