{"name": "Lacey-Mae", "slug": "lacey-mae", "boys": [], "girls": [{"year": 2001, "count": 3, "rank": 3998}, {"year": 2003, "count": 3, "rank": 4373}, {"year": 2004, "count": 5, "rank": 3197}, {"year": 2005, "count": 3, "rank": 4798}, {"year": 2006, "count": 9, "rank": 2320}, {"year": 2007, "count": 18, "rank": 1443}, {"year": 2008, "count": 42, "rank": 804}, {"year": 2009, "count": 36, "rank": 916}, {"year": 2010, "count": 60, "rank": 634}, {"year": 2011, "count": 80, "rank": 525}, {"year": 2012, "count": 107, "rank": 430}, {"year": 2013, "count": 106, "rank": 401}, {"year": 2014, "count": 66, "rank": 613}, {"year": 2015, "count": 72, "rank": 585}, {"year": 2016, "count": 63, "rank": 666}, {"year": 2017, "count": 45, "rank": 855}, {"year": 2018, "count": 38, "rank": 952}, {"year": 2019, "count": 44, "rank": 838}, {"year": 2020, "count": 19, "rank": 1556}, {"year": 2021, "count": 17, "rank": 1692}, {"year": 2022, "count": 16, "rank": 1767}, {"year": 2023, "count": 13, "rank": 2063}, {"year": 2024, "count": 8, "rank": 3015}]}