{"name": "Lenny", "slug": "lenny", "boys": [{"year": 1996, "count": 6, "rank": 1765}, {"year": 1997, "count": 6, "rank": 1761}, {"year": 1998, "count": 15, "rank": 958}, {"year": 1999, "count": 17, "rank": 906}, {"year": 2000, "count": 28, "rank": 651}, {"year": 2001, "count": 22, "rank": 786}, {"year": 2002, "count": 32, "rank": 611}, {"year": 2003, "count": 52, "rank": 469}, {"year": 2004, "count": 61, "rank": 443}, {"year": 2005, "count": 100, "rank": 320}, {"year": 2006, "count": 95, "rank": 360}, {"year": 2007, "count": 102, "rank": 360}, {"year": 2008, "count": 138, "rank": 298}, {"year": 2009, "count": 125, "rank": 319}, {"year": 2010, "count": 153, "rank": 292}, {"year": 2011, "count": 180, "rank": 265}, {"year": 2012, "count": 174, "rank": 269}, {"year": 2013, "count": 201, "rank": 248}, {"year": 2014, "count": 266, "rank": 213}, {"year": 2015, "count": 253, "rank": 222}, {"year": 2016, "count": 271, "rank": 207}, {"year": 2017, "count": 360, "rank": 158}, {"year": 2018, "count": 372, "rank": 152}, {"year": 2019, "count": 369, "rank": 151}, {"year": 2020, "count": 344, "rank": 154}, {"year": 2021, "count": 373, "rank": 153}, {"year": 2022, "count": 349, "rank": 153}, {"year": 2023, "count": 373, "rank": 140}, {"year": 2024, "count": 382, "rank": 142}], "girls": [{"year": 2015, "count": 3, "rank": 5730}, {"year": 2021, "count": 4, "rank": 4634}, {"year": 2022, "count": 4, "rank": 4645}, {"year": 2024, "count": 6, "rank": 3695}]}