{"name": "Louay", "slug": "louay", "boys": [{"year": 2009, "count": 4, "rank": 3744}, {"year": 2011, "count": 4, "rank": 3830}, {"year": 2013, "count": 4, "rank": 3822}, {"year": 2014, "count": 3, "rank": 4632}, {"year": 2015, "count": 3, "rank": 4747}, {"year": 2016, "count": 4, "rank": 4023}, {"year": 2018, "count": 3, "rank": 4749}, {"year": 2021, "count": 3, "rank": 4789}, {"year": 2022, "count": 4, "rank": 4001}, {"year": 2023, "count": 5, "rank": 3523}, {"year": 2024, "count": 10, "rank": 2263}], "girls": []}