{"name": "Madeeha", "slug": "madeeha", "boys": [], "girls": [{"year": 1996, "count": 9, "rank": 1755}, {"year": 1997, "count": 10, "rank": 1666}, {"year": 1998, "count": 11, "rank": 1571}, {"year": 1999, "count": 11, "rank": 1557}, {"year": 2000, "count": 17, "rank": 1139}, {"year": 2001, "count": 17, "rank": 1170}, {"year": 2002, "count": 17, "rank": 1192}, {"year": 2003, "count": 11, "rank": 1722}, {"year": 2004, "count": 15, "rank": 1459}, {"year": 2005, "count": 23, "rank": 1082}, {"year": 2006, "count": 23, "rank": 1153}, {"year": 2007, "count": 15, "rank": 1656}, {"year": 2008, "count": 25, "rank": 1176}, {"year": 2009, "count": 33, "rank": 982}, {"year": 2010, "count": 27, "rank": 1180}, {"year": 2011, "count": 29, "rank": 1149}, {"year": 2012, "count": 20, "rank": 1525}, {"year": 2013, "count": 19, "rank": 1587}, {"year": 2014, "count": 21, "rank": 1456}, {"year": 2015, "count": 20, "rank": 1549}, {"year": 2016, "count": 14, "rank": 2008}, {"year": 2017, "count": 17, "rank": 1733}, {"year": 2018, "count": 14, "rank": 1977}, {"year": 2019, "count": 8, "rank": 2869}, {"year": 2020, "count": 11, "rank": 2300}, {"year": 2021, "count": 9, "rank": 2711}, {"year": 2022, "count": 10, "rank": 2488}, {"year": 2023, "count": 13, "rank": 2063}, {"year": 2024, "count": 13, "rank": 2115}]}