{"name": "Monroe", "slug": "monroe", "boys": [{"year": 2008, "count": 3, "rank": 4432}, {"year": 2011, "count": 5, "rank": 3300}, {"year": 2012, "count": 5, "rank": 3416}, {"year": 2013, "count": 16, "rank": 1462}, {"year": 2014, "count": 7, "rank": 2690}, {"year": 2015, "count": 15, "rank": 1586}, {"year": 2016, "count": 15, "rank": 1627}, {"year": 2017, "count": 14, "rank": 1703}, {"year": 2018, "count": 19, "rank": 1324}, {"year": 2019, "count": 13, "rank": 1745}, {"year": 2020, "count": 19, "rank": 1314}, {"year": 2021, "count": 16, "rank": 1516}, {"year": 2022, "count": 19, "rank": 1366}, {"year": 2023, "count": 22, "rank": 1243}, {"year": 2024, "count": 15, "rank": 1675}], "girls": [{"year": 2011, "count": 5, "rank": 4049}, {"year": 2012, "count": 11, "rank": 2338}, {"year": 2013, "count": 16, "rank": 1774}, {"year": 2014, "count": 20, "rank": 1501}, {"year": 2015, "count": 31, "rank": 1114}, {"year": 2016, "count": 22, "rank": 1472}, {"year": 2017, "count": 29, "rank": 1184}, {"year": 2018, "count": 38, "rank": 952}, {"year": 2019, "count": 35, "rank": 996}, {"year": 2020, "count": 37, "rank": 941}, {"year": 2021, "count": 42, "rank": 840}, {"year": 2022, "count": 35, "rank": 982}, {"year": 2023, "count": 45, "rank": 794}, {"year": 2024, "count": 52, "rank": 722}]}