{"name": "Nixon", "slug": "nixon", "boys": [{"year": 1997, "count": 3, "rank": 2859}, {"year": 2003, "count": 3, "rank": 3467}, {"year": 2006, "count": 4, "rank": 3385}, {"year": 2007, "count": 4, "rank": 3589}, {"year": 2009, "count": 5, "rank": 3227}, {"year": 2011, "count": 4, "rank": 3830}, {"year": 2012, "count": 10, "rank": 2117}, {"year": 2013, "count": 14, "rank": 1617}, {"year": 2014, "count": 9, "rank": 2248}, {"year": 2015, "count": 12, "rank": 1902}, {"year": 2016, "count": 16, "rank": 1570}, {"year": 2017, "count": 19, "rank": 1339}, {"year": 2018, "count": 12, "rank": 1875}, {"year": 2019, "count": 20, "rank": 1253}, {"year": 2020, "count": 11, "rank": 1935}, {"year": 2021, "count": 11, "rank": 1984}, {"year": 2022, "count": 12, "rank": 1879}, {"year": 2023, "count": 4, "rank": 4107}, {"year": 2024, "count": 8, "rank": 2671}], "girls": []}