{"name": "Patience", "slug": "patience", "boys": [], "girls": [{"year": 1996, "count": 9, "rank": 1755}, {"year": 1997, "count": 5, "rank": 2738}, {"year": 1998, "count": 4, "rank": 3142}, {"year": 1999, "count": 5, "rank": 2770}, {"year": 2000, "count": 8, "rank": 1995}, {"year": 2001, "count": 5, "rank": 2783}, {"year": 2002, "count": 9, "rank": 1928}, {"year": 2003, "count": 6, "rank": 2727}, {"year": 2004, "count": 16, "rank": 1383}, {"year": 2005, "count": 26, "rank": 990}, {"year": 2006, "count": 31, "rank": 928}, {"year": 2007, "count": 22, "rank": 1234}, {"year": 2008, "count": 27, "rank": 1093}, {"year": 2009, "count": 22, "rank": 1325}, {"year": 2010, "count": 27, "rank": 1180}, {"year": 2011, "count": 19, "rank": 1545}, {"year": 2012, "count": 17, "rank": 1720}, {"year": 2013, "count": 17, "rank": 1707}, {"year": 2014, "count": 14, "rank": 1966}, {"year": 2015, "count": 15, "rank": 1865}, {"year": 2016, "count": 10, "rank": 2547}, {"year": 2017, "count": 9, "rank": 2706}, {"year": 2018, "count": 8, "rank": 2901}, {"year": 2019, "count": 7, "rank": 3151}, {"year": 2020, "count": 7, "rank": 3117}, {"year": 2021, "count": 3, "rank": 5581}, {"year": 2022, "count": 6, "rank": 3533}, {"year": 2023, "count": 4, "rank": 4709}, {"year": 2024, "count": 5, "rank": 4192}]}