{"name": "Pranay", "slug": "pranay", "boys": [{"year": 1996, "count": 5, "rank": 2020}, {"year": 1997, "count": 3, "rank": 2859}, {"year": 1998, "count": 5, "rank": 2074}, {"year": 1999, "count": 4, "rank": 2425}, {"year": 2000, "count": 11, "rank": 1241}, {"year": 2001, "count": 5, "rank": 2220}, {"year": 2002, "count": 4, "rank": 2636}, {"year": 2003, "count": 7, "rank": 1962}, {"year": 2004, "count": 11, "rank": 1498}, {"year": 2005, "count": 7, "rank": 2174}, {"year": 2006, "count": 11, "rank": 1643}, {"year": 2007, "count": 20, "rank": 1169}, {"year": 2008, "count": 15, "rank": 1457}, {"year": 2009, "count": 10, "rank": 1981}, {"year": 2010, "count": 11, "rank": 1911}, {"year": 2011, "count": 12, "rank": 1788}, {"year": 2012, "count": 6, "rank": 3039}, {"year": 2013, "count": 6, "rank": 2954}, {"year": 2014, "count": 4, "rank": 3895}, {"year": 2015, "count": 10, "rank": 2150}, {"year": 2016, "count": 4, "rank": 4023}, {"year": 2017, "count": 4, "rank": 3996}, {"year": 2018, "count": 4, "rank": 3959}, {"year": 2019, "count": 3, "rank": 4702}, {"year": 2024, "count": 6, "rank": 3254}], "girls": []}