{"name": "Rebekka", "slug": "rebekka", "boys": [], "girls": [{"year": 1996, "count": 44, "rank": 562}, {"year": 1997, "count": 35, "rank": 689}, {"year": 1998, "count": 26, "rank": 846}, {"year": 1999, "count": 28, "rank": 794}, {"year": 2000, "count": 23, "rank": 930}, {"year": 2001, "count": 20, "rank": 1025}, {"year": 2002, "count": 12, "rank": 1530}, {"year": 2003, "count": 19, "rank": 1176}, {"year": 2004, "count": 7, "rank": 2530}, {"year": 2005, "count": 10, "rank": 2084}, {"year": 2006, "count": 10, "rank": 2137}, {"year": 2007, "count": 8, "rank": 2627}, {"year": 2008, "count": 8, "rank": 2721}, {"year": 2009, "count": 12, "rank": 2019}, {"year": 2011, "count": 4, "rank": 4764}, {"year": 2013, "count": 3, "rank": 5742}]}