{"name": "Romy", "slug": "romy", "boys": [{"year": 2003, "count": 3, "rank": 3467}, {"year": 2004, "count": 3, "rank": 3651}, {"year": 2006, "count": 3, "rank": 4052}, {"year": 2007, "count": 3, "rank": 4333}, {"year": 2010, "count": 3, "rank": 4678}, {"year": 2016, "count": 4, "rank": 4023}, {"year": 2018, "count": 7, "rank": 2693}, {"year": 2019, "count": 8, "rank": 2488}, {"year": 2020, "count": 10, "rank": 2076}, {"year": 2021, "count": 11, "rank": 1984}, {"year": 2022, "count": 10, "rank": 2165}, {"year": 2023, "count": 14, "rank": 1701}, {"year": 2024, "count": 19, "rank": 1402}], "girls": [{"year": 1996, "count": 31, "rank": 736}, {"year": 1997, "count": 19, "rank": 1045}, {"year": 1998, "count": 36, "rank": 672}, {"year": 1999, "count": 36, "rank": 663}, {"year": 2000, "count": 50, "rank": 545}, {"year": 2001, "count": 42, "rank": 612}, {"year": 2002, "count": 36, "rank": 722}, {"year": 2003, "count": 41, "rank": 690}, {"year": 2004, "count": 27, "rank": 948}, {"year": 2005, "count": 24, "rank": 1045}, {"year": 2006, "count": 27, "rank": 1031}, {"year": 2007, "count": 40, "rank": 809}, {"year": 2008, "count": 44, "rank": 779}, {"year": 2009, "count": 36, "rank": 916}, {"year": 2010, "count": 45, "rank": 801}, {"year": 2011, "count": 44, "rank": 830}, {"year": 2012, "count": 41, "rank": 902}, {"year": 2013, "count": 33, "rank": 1075}, {"year": 2014, "count": 40, "rank": 920}, {"year": 2015, "count": 51, "rank": 760}, {"year": 2016, "count": 49, "rank": 790}, {"year": 2017, "count": 58, "rank": 701}, {"year": 2018, "count": 67, "rank": 614}, {"year": 2019, "count": 80, "rank": 510}, {"year": 2020, "count": 91, "rank": 452}, {"year": 2021, "count": 121, "rank": 378}, {"year": 2022, "count": 110, "rank": 391}, {"year": 2023, "count": 163, "rank": 273}, {"year": 2024, "count": 263, "rank": 187}]}