{"name": "Simranjeet", "slug": "simranjeet", "boys": [{"year": 1996, "count": 4, "rank": 2357}, {"year": 2001, "count": 5, "rank": 2220}, {"year": 2003, "count": 3, "rank": 3467}], "girls": [{"year": 1996, "count": 13, "rank": 1364}, {"year": 1997, "count": 5, "rank": 2738}, {"year": 1998, "count": 6, "rank": 2407}, {"year": 1999, "count": 8, "rank": 1970}, {"year": 2000, "count": 3, "rank": 3912}, {"year": 2001, "count": 4, "rank": 3262}, {"year": 2002, "count": 5, "rank": 2868}, {"year": 2003, "count": 3, "rank": 4373}, {"year": 2006, "count": 3, "rank": 5061}, {"year": 2007, "count": 3, "rank": 5201}, {"year": 2009, "count": 6, "rank": 3422}, {"year": 2010, "count": 4, "rank": 4688}, {"year": 2011, "count": 4, "rank": 4764}]}