{"name": "Taneesha", "slug": "taneesha", "boys": [], "girls": [{"year": 1996, "count": 4, "rank": 3126}, {"year": 1997, "count": 5, "rank": 2738}, {"year": 1999, "count": 3, "rank": 3900}, {"year": 2002, "count": 4, "rank": 3409}, {"year": 2006, "count": 5, "rank": 3548}, {"year": 2007, "count": 4, "rank": 4294}, {"year": 2008, "count": 7, "rank": 3005}, {"year": 2009, "count": 3, "rank": 5556}, {"year": 2010, "count": 6, "rank": 3533}, {"year": 2011, "count": 11, "rank": 2275}, {"year": 2012, "count": 3, "rank": 5876}]}