{"name": "Tate", "slug": "tate", "boys": [{"year": 1996, "count": 21, "rank": 728}, {"year": 1997, "count": 22, "rank": 725}, {"year": 1998, "count": 28, "rank": 629}, {"year": 1999, "count": 37, "rank": 528}, {"year": 2000, "count": 37, "rank": 527}, {"year": 2001, "count": 20, "rank": 842}, {"year": 2002, "count": 30, "rank": 656}, {"year": 2003, "count": 38, "rank": 586}, {"year": 2004, "count": 39, "rank": 625}, {"year": 2005, "count": 51, "rank": 525}, {"year": 2006, "count": 54, "rank": 543}, {"year": 2007, "count": 47, "rank": 622}, {"year": 2008, "count": 51, "rank": 613}, {"year": 2009, "count": 42, "rank": 711}, {"year": 2010, "count": 53, "rank": 615}, {"year": 2011, "count": 72, "rank": 501}, {"year": 2012, "count": 115, "rank": 367}, {"year": 2013, "count": 140, "rank": 310}, {"year": 2014, "count": 150, "rank": 305}, {"year": 2015, "count": 125, "rank": 359}, {"year": 2016, "count": 124, "rank": 373}, {"year": 2017, "count": 121, "rank": 377}, {"year": 2018, "count": 124, "rank": 366}, {"year": 2019, "count": 104, "rank": 410}, {"year": 2020, "count": 127, "rank": 352}, {"year": 2021, "count": 103, "rank": 412}, {"year": 2022, "count": 119, "rank": 358}, {"year": 2023, "count": 118, "rank": 357}, {"year": 2024, "count": 119, "rank": 364}], "girls": [{"year": 1996, "count": 6, "rank": 2350}, {"year": 1997, "count": 6, "rank": 2411}, {"year": 1998, "count": 7, "rank": 2165}, {"year": 1999, "count": 6, "rank": 2444}, {"year": 2000, "count": 11, "rank": 1594}, {"year": 2001, "count": 15, "rank": 1305}, {"year": 2002, "count": 13, "rank": 1442}, {"year": 2003, "count": 17, "rank": 1269}, {"year": 2004, "count": 8, "rank": 2278}, {"year": 2005, "count": 14, "rank": 1589}, {"year": 2006, "count": 10, "rank": 2137}, {"year": 2007, "count": 11, "rank": 2085}, {"year": 2008, "count": 9, "rank": 2487}, {"year": 2009, "count": 8, "rank": 2759}, {"year": 2010, "count": 6, "rank": 3533}, {"year": 2011, "count": 6, "rank": 3549}, {"year": 2012, "count": 13, "rank": 2095}, {"year": 2013, "count": 6, "rank": 3536}, {"year": 2014, "count": 4, "rank": 4684}, {"year": 2015, "count": 5, "rank": 4103}, {"year": 2016, "count": 3, "rank": 5785}, {"year": 2017, "count": 6, "rank": 3583}, {"year": 2018, "count": 8, "rank": 2901}, {"year": 2019, "count": 3, "rank": 5591}, {"year": 2021, "count": 5, "rank": 3961}, {"year": 2022, "count": 3, "rank": 5669}, {"year": 2023, "count": 4, "rank": 4709}, {"year": 2024, "count": 5, "rank": 4192}]}