{"name": "Tess", "slug": "tess", "boys": [], "girls": [{"year": 1996, "count": 37, "rank": 643}, {"year": 1997, "count": 35, "rank": 689}, {"year": 1998, "count": 38, "rank": 649}, {"year": 1999, "count": 34, "rank": 691}, {"year": 2000, "count": 61, "rank": 485}, {"year": 2001, "count": 49, "rank": 565}, {"year": 2002, "count": 67, "rank": 463}, {"year": 2003, "count": 56, "rank": 545}, {"year": 2004, "count": 76, "rank": 459}, {"year": 2005, "count": 88, "rank": 423}, {"year": 2006, "count": 85, "rank": 456}, {"year": 2007, "count": 61, "rank": 589}, {"year": 2008, "count": 72, "rank": 532}, {"year": 2009, "count": 95, "rank": 438}, {"year": 2010, "count": 81, "rank": 499}, {"year": 2011, "count": 79, "rank": 530}, {"year": 2012, "count": 67, "rank": 624}, {"year": 2013, "count": 59, "rank": 676}, {"year": 2014, "count": 51, "rank": 763}, {"year": 2015, "count": 60, "rank": 674}, {"year": 2016, "count": 49, "rank": 790}, {"year": 2017, "count": 37, "rank": 982}, {"year": 2018, "count": 32, "rank": 1083}, {"year": 2019, "count": 35, "rank": 996}, {"year": 2020, "count": 24, "rank": 1313}, {"year": 2021, "count": 18, "rank": 1628}, {"year": 2022, "count": 15, "rank": 1849}, {"year": 2023, "count": 16, "rank": 1774}, {"year": 2024, "count": 9, "rank": 2771}]}