{"name": "Zahra", "slug": "zahra", "boys": [], "girls": [{"year": 1996, "count": 106, "rank": 331}, {"year": 1997, "count": 153, "rank": 256}, {"year": 1998, "count": 157, "rank": 254}, {"year": 1999, "count": 152, "rank": 260}, {"year": 2000, "count": 181, "rank": 226}, {"year": 2001, "count": 184, "rank": 219}, {"year": 2002, "count": 227, "rank": 188}, {"year": 2003, "count": 223, "rank": 211}, {"year": 2004, "count": 235, "rank": 197}, {"year": 2005, "count": 278, "rank": 183}, {"year": 2006, "count": 338, "rank": 158}, {"year": 2007, "count": 352, "rank": 155}, {"year": 2008, "count": 396, "rank": 136}, {"year": 2009, "count": 361, "rank": 152}, {"year": 2010, "count": 348, "rank": 151}, {"year": 2011, "count": 345, "rank": 154}, {"year": 2012, "count": 393, "rank": 144}, {"year": 2013, "count": 314, "rank": 167}, {"year": 2014, "count": 353, "rank": 158}, {"year": 2015, "count": 361, "rank": 149}, {"year": 2016, "count": 359, "rank": 154}, {"year": 2017, "count": 345, "rank": 162}, {"year": 2018, "count": 333, "rank": 162}, {"year": 2019, "count": 320, "rank": 156}, {"year": 2020, "count": 289, "rank": 174}, {"year": 2021, "count": 269, "rank": 190}, {"year": 2022, "count": 333, "rank": 147}, {"year": 2023, "count": 346, "rank": 142}, {"year": 2024, "count": 387, "rank": 126}]}