{"name": "Ahlam", "slug": "ahlam", "sex": "girls", "minYears": 5, "neighbors": [{"name": "Rosalyn", "slug": "rosalyn", "sse": 18146.05369436741, "overlapYears": 29}, {"name": "Naina", "slug": "naina", "sse": 23702.73636674881, "overlapYears": 29}, {"name": "Marcella", "slug": "marcella", "sse": 46697.048768520355, "overlapYears": 29}, {"name": "Seher", "slug": "seher", "sse": 48346.67684733868, "overlapYears": 29}, {"name": "Saliha", "slug": "saliha", "sse": 98018.81822657585, "overlapYears": 29}, {"name": "Heba", "slug": "heba", "sse": 188228.13497447968, "overlapYears": 29}, {"name": "Lianna", "slug": "lianna", "sse": 203736.6975402832, "overlapYears": 29}, {"name": "Inez", "slug": "inez", "sse": 209441.21630477905, "overlapYears": 28}, {"name": "Maryama", "slug": "maryama", "sse": 279103.7893896103, "overlapYears": 28}, {"name": "Cynthia", "slug": "cynthia", "sse": 293377.50197041035, "overlapYears": 29}]}