{"name": "Benita", "slug": "benita", "sex": "girls", "minYears": 5, "neighbors": [{"name": "Danae", "slug": "danae", "sse": 106525.09159362316, "overlapYears": 28}, {"name": "Riona", "slug": "riona", "sse": 140040.4483613968, "overlapYears": 29}, {"name": "Catarina", "slug": "catarina", "sse": 152009.37692260742, "overlapYears": 29}, {"name": "Tallula", "slug": "tallula", "sse": 155560.47556352615, "overlapYears": 28}, {"name": "Marion", "slug": "marion", "sse": 216446.2514076233, "overlapYears": 29}, {"name": "Ramla", "slug": "ramla", "sse": 233637.08841133118, "overlapYears": 29}, {"name": "Caterina", "slug": "caterina", "sse": 234839.44970661402, "overlapYears": 29}, {"name": "Micaela", "slug": "micaela", "sse": 261585.52322006226, "overlapYears": 29}, {"name": "Peace", "slug": "peace", "sse": 288330.103477478, "overlapYears": 27}, {"name": "Andie", "slug": "andie", "sse": 311603.3500366211, "overlapYears": 29}]}