{"name": "Catarina", "slug": "catarina", "sex": "girls", "minYears": 5, "neighbors": [{"name": "Andie", "slug": "andie", "sse": 31225.226108551025, "overlapYears": 29}, {"name": "Micaela", "slug": "micaela", "sse": 55160.32266010344, "overlapYears": 29}, {"name": "Danae", "slug": "danae", "sse": 119640.70944833755, "overlapYears": 28}, {"name": "Benita", "slug": "benita", "sse": 152009.37692260742, "overlapYears": 29}, {"name": "Raquel", "slug": "raquel", "sse": 190656.28324985504, "overlapYears": 29}, {"name": "Caterina", "slug": "caterina", "sse": 410880.8665008545, "overlapYears": 29}, {"name": "Tallula", "slug": "tallula", "sse": 428557.15925979614, "overlapYears": 28}, {"name": "Mary-Kate", "slug": "mary-kate", "sse": 430759.52888762206, "overlapYears": 29}, {"name": "Carissa", "slug": "carissa", "sse": 433734.3019981384, "overlapYears": 29}, {"name": "Rima", "slug": "rima", "sse": 506693.72117614746, "overlapYears": 29}]}