{"name": "Drew", "slug": "drew", "sex": "girls", "minYears": 5, "neighbors": [{"name": "Maisha", "slug": "maisha", "sse": 19388.53990149498, "overlapYears": 29}, {"name": "Anjali", "slug": "anjali", "sse": 34923.404433488846, "overlapYears": 29}, {"name": "Maariyah", "slug": "maariyah", "sse": 75911.21921187639, "overlapYears": 29}, {"name": "Kezia", "slug": "kezia", "sse": 80359.31724134088, "overlapYears": 29}, {"name": "Marissa", "slug": "marissa", "sse": 89053.37241411209, "overlapYears": 29}, {"name": "Sharon", "slug": "sharon", "sse": 94257.90689648688, "overlapYears": 29}, {"name": "Saba", "slug": "saba", "sse": 95148.87684726715, "overlapYears": 29}, {"name": "Bridie", "slug": "bridie", "sse": 102602.20394134521, "overlapYears": 29}, {"name": "Alison", "slug": "alison", "sse": 108517.83448274434, "overlapYears": 29}, {"name": "Rabia", "slug": "rabia", "sse": 147797.53497600555, "overlapYears": 29}]}