{"name": "Emmeline", "slug": "emmeline", "sex": "girls", "minYears": 5, "neighbors": [{"name": "Paisley", "slug": "paisley", "sse": 13104.152709353715, "overlapYears": 29}, {"name": "Safaa", "slug": "safaa", "sse": 20693.59162557125, "overlapYears": 29}, {"name": "Marley", "slug": "marley", "sse": 84050.10886669159, "overlapYears": 29}, {"name": "Vienna", "slug": "vienna", "sse": 102699.62118208408, "overlapYears": 29}, {"name": "Indigo", "slug": "indigo", "sse": 154657.13990163803, "overlapYears": 29}, {"name": "Selena", "slug": "selena", "sse": 166578.34926128387, "overlapYears": 29}, {"name": "Dakota", "slug": "dakota", "sse": 170182.30738925934, "overlapYears": 29}, {"name": "Betty", "slug": "betty", "sse": 183149.6088670045, "overlapYears": 29}, {"name": "Indiana", "slug": "indiana", "sse": 191159.3172416687, "overlapYears": 29}, {"name": "Amalia", "slug": "amalia", "sse": 216221.5177345276, "overlapYears": 29}]}