{"name": "Isabel", "slug": "isabel", "sex": "girls", "minYears": 5, "neighbors": [{"name": "Victoria", "slug": "victoria", "sse": 215.40394088678477, "overlapYears": 29}, {"name": "Niamh", "slug": "niamh", "sse": 1801.4310344904661, "overlapYears": 29}, {"name": "Lydia", "slug": "lydia", "sse": 2994.521674886346, "overlapYears": 29}, {"name": "Francesca", "slug": "francesca", "sse": 3722.6226601600647, "overlapYears": 29}, {"name": "Sarah", "slug": "sarah", "sse": 4452.30550415162, "overlapYears": 29}, {"name": "Zoe", "slug": "zoe", "sse": 5379.559113301337, "overlapYears": 29}, {"name": "Mollie", "slug": "mollie", "sse": 6666.738423646428, "overlapYears": 29}, {"name": "Alexandra", "slug": "alexandra", "sse": 10837.04876846075, "overlapYears": 29}, {"name": "Isobel", "slug": "isobel", "sse": 14480.224630475044, "overlapYears": 29}, {"name": "Anna", "slug": "anna", "sse": 18130.738423645496, "overlapYears": 29}]}