{"name": "Maisie", "slug": "maisie", "sex": "girls", "minYears": 5, "neighbors": [{"name": "Rosie", "slug": "rosie", "sse": 1962.3527093597222, "overlapYears": 29}, {"name": "Imogen", "slug": "imogen", "sse": 4338.467487722635, "overlapYears": 29}, {"name": "Isabelle", "slug": "isabelle", "sse": 6681.674384236336, "overlapYears": 29}, {"name": "Erin", "slug": "erin", "sse": 6707.3399013876915, "overlapYears": 29}, {"name": "Millie", "slug": "millie", "sse": 8325.98965517059, "overlapYears": 29}, {"name": "Ruby", "slug": "ruby", "sse": 8853.10541872005, "overlapYears": 29}, {"name": "Harriet", "slug": "harriet", "sse": 9329.03990161419, "overlapYears": 29}, {"name": "Sophia", "slug": "sophia", "sse": 10355.712315261364, "overlapYears": 29}, {"name": "Poppy", "slug": "poppy", "sse": 13398.53990149498, "overlapYears": 29}, {"name": "Freya", "slug": "freya", "sse": 13503.876847326756, "overlapYears": 29}]}