{"name": "Ramla", "slug": "ramla", "sex": "girls", "minYears": 5, "neighbors": [{"name": "Ameenah", "slug": "ameenah", "sse": 16923.607250631787, "overlapYears": 29}, {"name": "Riona", "slug": "riona", "sse": 25924.55302121398, "overlapYears": 29}, {"name": "Nidhi", "slug": "nidhi", "sse": 45719.39896941185, "overlapYears": 28}, {"name": "Caterina", "slug": "caterina", "sse": 63202.61158800125, "overlapYears": 29}, {"name": "Gwyneth", "slug": "gwyneth", "sse": 119540.41250228882, "overlapYears": 29}, {"name": "Hajira", "slug": "hajira", "sse": 138344.11174583435, "overlapYears": 29}, {"name": "Marion", "slug": "marion", "sse": 142206.538012743, "overlapYears": 29}, {"name": "Anna-Maria", "slug": "anna-maria", "sse": 153831.47997617722, "overlapYears": 29}, {"name": "Danae", "slug": "danae", "sse": 172436.31210327148, "overlapYears": 28}, {"name": "Trudy", "slug": "trudy", "sse": 194892.7464427948, "overlapYears": 29}]}