{"name": "Winnie", "slug": "winnie", "sex": "girls", "minYears": 5, "neighbors": [{"name": "Noa", "slug": "noa", "sse": 11003.090210460126, "overlapYears": 28}, {"name": "Aleksandra", "slug": "aleksandra", "sse": 38778.333005189896, "overlapYears": 29}, {"name": "Orlaith", "slug": "orlaith", "sse": 68364.55911207199, "overlapYears": 29}, {"name": "Daphne", "slug": "daphne", "sse": 143056.8940886557, "overlapYears": 29}, {"name": "Daisy-Mae", "slug": "daisy-mae", "sse": 167426.36945801973, "overlapYears": 29}, {"name": "Alma", "slug": "alma", "sse": 183203.6605911255, "overlapYears": 29}, {"name": "Maira", "slug": "maira", "sse": 280144.4453201294, "overlapYears": 29}, {"name": "Milena", "slug": "milena", "sse": 312973.5596075058, "overlapYears": 29}, {"name": "Ameerah", "slug": "ameerah", "sse": 320003.63300704956, "overlapYears": 29}, {"name": "Peggy", "slug": "peggy", "sse": 330826.7384236157, "overlapYears": 29}]}