{"name": "Crystal", "sex": "girls", "ranks": [{"year": 1996, "rank": 327}, {"year": 1997, "rank": 338}, {"year": 1998, "rank": 284}, {"year": 1999, "rank": 320}, {"year": 2000, "rank": 349}, {"year": 2001, "rank": 305}, {"year": 2002, "rank": 302}, {"year": 2003, "rank": 332}, {"year": 2004, "rank": 283}, {"year": 2005, "rank": 269}, {"year": 2006, "rank": 260}, {"year": 2007, "rank": 218}, {"year": 2008, "rank": 220}, {"year": 2009, "rank": 224}, {"year": 2010, "rank": 276}, {"year": 2011, "rank": 343}, {"year": 2012, "rank": 341}, {"year": 2013, "rank": 358}, {"year": 2014, "rank": 427}, {"year": 2015, "rank": 560}, {"year": 2016, "rank": 481}, {"year": 2017, "rank": 683}, {"year": 2018, "rank": 729}, {"year": 2019, "rank": 806}, {"year": 2020, "rank": 765}, {"year": 2021, "rank": 747}, {"year": 2022, "rank": 1326}, {"year": 2023, "rank": 1135}, {"year": 2024, "rank": 1353}]}