{"name": "Samina", "sex": "girls", "ranks": [{"year": 1996, "rank": 594}, {"year": 1997, "rank": 803}, {"year": 1998, "rank": 1165}, {"year": 1999, "rank": 1018}, {"year": 2000, "rank": 930}, {"year": 2001, "rank": 779}, {"year": 2002, "rank": 861}, {"year": 2003, "rank": 996}, {"year": 2004, "rank": 1106}, {"year": 2005, "rank": 1200}, {"year": 2006, "rank": 1585}, {"year": 2007, "rank": 1965}, {"year": 2008, "rank": 2292}, {"year": 2009, "rank": 2148}, {"year": 2010, "rank": 3156}, {"year": 2011, "rank": 1374}, {"year": 2012, "rank": 2095}, {"year": 2013, "rank": 3536}, {"year": 2015, "rank": 2945}, {"year": 2016, "rank": 4763}, {"year": 2017, "rank": 4763}, {"year": 2018, "rank": 3178}, {"year": 2019, "rank": 5591}, {"year": 2020, "rank": 4535}]}