{"name": "Sawdah", "sex": "girls", "ranks": [{"year": 1999, "rank": 2770}, {"year": 2001, "rank": 2783}, {"year": 2002, "rank": 3409}, {"year": 2003, "rank": 2436}, {"year": 2005, "rank": 4798}, {"year": 2007, "rank": 2895}, {"year": 2009, "rank": 4564}, {"year": 2010, "rank": 4688}, {"year": 2011, "rank": 4764}, {"year": 2012, "rank": 3681}, {"year": 2013, "rank": 3160}, {"year": 2015, "rank": 1961}, {"year": 2016, "rank": 2008}, {"year": 2017, "rank": 2502}, {"year": 2018, "rank": 4684}, {"year": 2020, "rank": 3447}, {"year": 2021, "rank": 2711}, {"year": 2022, "rank": 2888}, {"year": 2023, "rank": 3218}, {"year": 2024, "rank": 2000}]}