{"name": "Tahiya", "sex": "girls", "ranks": [{"year": 1997, "rank": 3824}, {"year": 1998, "rank": 3142}, {"year": 1999, "rank": 1970}, {"year": 2000, "rank": 3247}, {"year": 2001, "rank": 2023}, {"year": 2003, "rank": 1722}, {"year": 2004, "rank": 1715}, {"year": 2005, "rank": 2247}, {"year": 2006, "rank": 2137}, {"year": 2007, "rank": 2895}, {"year": 2008, "rank": 2487}, {"year": 2009, "rank": 1526}, {"year": 2010, "rank": 3533}, {"year": 2011, "rank": 4049}, {"year": 2012, "rank": 5876}, {"year": 2013, "rank": 2887}, {"year": 2014, "rank": 2464}, {"year": 2015, "rank": 2195}, {"year": 2016, "rank": 4763}, {"year": 2018, "rank": 3178}, {"year": 2019, "rank": 4686}, {"year": 2020, "rank": 4535}, {"year": 2023, "rank": 5687}]}