{"name": "Arsalan", "slug": "arsalan", "sex": "boys", "minYears": 5, "neighbors": [{"name": "Keshav", "slug": "keshav", "sse": 31086.52955687046, "overlapYears": 29}, {"name": "Tommi", "slug": "tommi", "sse": 44229.70305776596, "overlapYears": 28}, {"name": "Rene", "slug": "rene", "sse": 55891.558619976044, "overlapYears": 29}, {"name": "Kairon", "slug": "kairon", "sse": 70764.66408634186, "overlapYears": 27}, {"name": "Andrea", "slug": "andrea", "sse": 114177.13321447372, "overlapYears": 29}, {"name": "Kailan", "slug": "kailan", "sse": 128485.75566506386, "overlapYears": 29}, {"name": "Mazin", "slug": "mazin", "sse": 146852.42799013853, "overlapYears": 28}, {"name": "Codi", "slug": "codi", "sse": 193831.37585258484, "overlapYears": 29}, {"name": "Fenn", "slug": "fenn", "sse": 202981.71477794647, "overlapYears": 29}, {"name": "Kavin", "slug": "kavin", "sse": 253310.34489440918, "overlapYears": 28}]}