{"name": "Ashton", "slug": "ashton", "sex": "boys", "minYears": 5, "neighbors": [{"name": "Barnaby", "slug": "barnaby", "sse": 450.2862068959512, "overlapYears": 29}, {"name": "Adrian", "slug": "adrian", "sse": 4077.032019674778, "overlapYears": 29}, {"name": "Mustafa", "slug": "mustafa", "sse": 6849.383743822575, "overlapYears": 29}, {"name": "Francis", "slug": "francis", "sse": 15470.105418801308, "overlapYears": 29}, {"name": "Frank", "slug": "frank", "sse": 20319.424137949944, "overlapYears": 29}, {"name": "Robin", "slug": "robin", "sse": 25503.229556560516, "overlapYears": 29}, {"name": "Ismail", "slug": "ismail", "sse": 25954.952709376812, "overlapYears": 29}, {"name": "Rohan", "slug": "rohan", "sse": 30054.66305398941, "overlapYears": 29}, {"name": "Umar", "slug": "umar", "sse": 32148.15960597992, "overlapYears": 29}, {"name": "Zac", "slug": "zac", "sse": 36680.945320129395, "overlapYears": 29}]}