{"name": "Dan", "slug": "dan", "sex": "boys", "minYears": 5, "neighbors": [{"name": "Rhodri", "slug": "rhodri", "sse": 27793.56896531582, "overlapYears": 29}, {"name": "Jacques", "slug": "jacques", "sse": 86116.18472909927, "overlapYears": 29}, {"name": "Nabil", "slug": "nabil", "sse": 91203.88620710373, "overlapYears": 29}, {"name": "Humza", "slug": "humza", "sse": 92857.06206893921, "overlapYears": 29}, {"name": "Asad", "slug": "asad", "sse": 103485.50443267822, "overlapYears": 29}, {"name": "Che", "slug": "che", "sse": 110073.93152737617, "overlapYears": 29}, {"name": "Jonty", "slug": "jonty", "sse": 123446.81478023529, "overlapYears": 29}, {"name": "Terence", "slug": "terence", "sse": 129409.39852237701, "overlapYears": 29}, {"name": "Fabio", "slug": "fabio", "sse": 190206.4832496643, "overlapYears": 29}, {"name": "Jeffrey", "slug": "jeffrey", "sse": 199636.9536946714, "overlapYears": 29}]}