{"name": "Desmond", "slug": "desmond", "sex": "boys", "minYears": 5, "neighbors": [{"name": "Shlomo", "slug": "shlomo", "sse": 1980.248768478632, "overlapYears": 29}, {"name": "Kaif", "slug": "kaif", "sse": 19942.484119176865, "overlapYears": 28}, {"name": "Youcef", "slug": "youcef", "sse": 21302.88374376297, "overlapYears": 29}, {"name": "Parth", "slug": "parth", "sse": 22999.5389162302, "overlapYears": 29}, {"name": "Kalen", "slug": "kalen", "sse": 38719.87438423559, "overlapYears": 29}, {"name": "Umut", "slug": "umut", "sse": 60514.79753732681, "overlapYears": 29}, {"name": "Aleem", "slug": "aleem", "sse": 61468.74926114082, "overlapYears": 29}, {"name": "Keagan", "slug": "keagan", "sse": 73161.80788171291, "overlapYears": 29}, {"name": "Mubarak", "slug": "mubarak", "sse": 77195.73645353317, "overlapYears": 29}, {"name": "Hakim", "slug": "hakim", "sse": 83170.99064040184, "overlapYears": 29}]}