{"name": "Farhan", "slug": "farhan", "sex": "boys", "minYears": 5, "neighbors": [{"name": "Adnan", "slug": "adnan", "sse": 1476.2039408907294, "overlapYears": 29}, {"name": "Qasim", "slug": "qasim", "sse": 5612.004433512688, "overlapYears": 29}, {"name": "Nathanael", "slug": "nathanael", "sse": 15792.335467983037, "overlapYears": 29}, {"name": "Uzair", "slug": "uzair", "sse": 35042.695073843, "overlapYears": 29}, {"name": "Gethin", "slug": "gethin", "sse": 46545.575553417206, "overlapYears": 29}, {"name": "Amar", "slug": "amar", "sse": 50237.35172390938, "overlapYears": 29}, {"name": "Samir", "slug": "samir", "sse": 62779.88374328613, "overlapYears": 29}, {"name": "Danyal", "slug": "danyal", "sse": 86996.68472909927, "overlapYears": 29}, {"name": "Anton", "slug": "anton", "sse": 96220.74137878418, "overlapYears": 29}, {"name": "Dion", "slug": "dion", "sse": 105725.18669950962, "overlapYears": 29}]}