{"name": "Ken", "slug": "ken", "sex": "boys", "minYears": 5, "neighbors": [{"name": "Jolyon", "slug": "jolyon", "sse": 27890.3759906888, "overlapYears": 28}, {"name": "Charly", "slug": "charly", "sse": 52390.39916753769, "overlapYears": 28}, {"name": "Akhil", "slug": "akhil", "sse": 180921.2537574768, "overlapYears": 28}, {"name": "Charlton", "slug": "charlton", "sse": 188422.85410690308, "overlapYears": 28}, {"name": "Oluwaseun", "slug": "oluwaseun", "sse": 605982.1305872202, "overlapYears": 28}, {"name": "Clive", "slug": "clive", "sse": 761153.9078025818, "overlapYears": 28}, {"name": "Sadiq", "slug": "sadiq", "sse": 895964.1795272827, "overlapYears": 28}, {"name": "Ashvin", "slug": "ashvin", "sse": 974831.4752426147, "overlapYears": 27}, {"name": "Clifford", "slug": "clifford", "sse": 1105171.4673843384, "overlapYears": 28}, {"name": "Akbar", "slug": "akbar", "sse": 1290504.3671731353, "overlapYears": 28}]}