{"name": "Kevin", "slug": "kevin", "sex": "boys", "minYears": 5, "neighbors": [{"name": "Ahmed", "slug": "ahmed", "sse": 159.03645320236683, "overlapYears": 29}, {"name": "Abdul", "slug": "abdul", "sse": 899.972906395793, "overlapYears": 29}, {"name": "Hamza", "slug": "hamza", "sse": 4283.290147840977, "overlapYears": 29}, {"name": "Zain", "slug": "zain", "sse": 4566.741871921578, "overlapYears": 29}, {"name": "Spencer", "slug": "spencer", "sse": 6342.056157648563, "overlapYears": 29}, {"name": "Mohamed", "slug": "mohamed", "sse": 7923.783743798733, "overlapYears": 29}, {"name": "Maximilian", "slug": "maximilian", "sse": 8357.044827580452, "overlapYears": 29}, {"name": "Tristan", "slug": "tristan", "sse": 9630.403940916061, "overlapYears": 29}, {"name": "Omar", "slug": "omar", "sse": 10007.846798028797, "overlapYears": 29}, {"name": "Syed", "slug": "syed", "sse": 10234.036453202367, "overlapYears": 29}]}