{"name": "Pascal", "slug": "pascal", "sex": "boys", "minYears": 5, "neighbors": [{"name": "Dhillon", "slug": "dhillon", "sse": 4269.08147714287, "overlapYears": 29}, {"name": "Salmaan", "slug": "salmaan", "sse": 88106.728910923, "overlapYears": 29}, {"name": "Nasser", "slug": "nasser", "sse": 91039.97650337219, "overlapYears": 29}, {"name": "Kester", "slug": "kester", "sse": 103262.65768384933, "overlapYears": 29}, {"name": "Hywel", "slug": "hywel", "sse": 137083.91292095184, "overlapYears": 29}, {"name": "Dino", "slug": "dino", "sse": 151627.70842313766, "overlapYears": 29}, {"name": "Cadan", "slug": "cadan", "sse": 157898.01156029105, "overlapYears": 28}, {"name": "Faraz", "slug": "faraz", "sse": 175052.54819965363, "overlapYears": 29}, {"name": "Yahye", "slug": "yahye", "sse": 178843.52550125122, "overlapYears": 29}, {"name": "Azhar", "slug": "azhar", "sse": 194740.56577205658, "overlapYears": 29}]}