{"name": "Reid", "slug": "reid", "sex": "boys", "minYears": 5, "neighbors": [{"name": "Md", "slug": "md", "sse": 5577.98325124383, "overlapYears": 29}, {"name": "Sulayman", "slug": "sulayman", "sse": 15931.84926110506, "overlapYears": 29}, {"name": "Jovan", "slug": "jovan", "sse": 25267.846798033715, "overlapYears": 29}, {"name": "Lawson", "slug": "lawson", "sse": 45614.12610864639, "overlapYears": 29}, {"name": "Herbie", "slug": "herbie", "sse": 67281.66256141663, "overlapYears": 29}, {"name": "Deen", "slug": "deen", "sse": 79830.73235964775, "overlapYears": 28}, {"name": "Rylee", "slug": "rylee", "sse": 106266.64881038666, "overlapYears": 26}, {"name": "Matthias", "slug": "matthias", "sse": 109995.0078818798, "overlapYears": 29}, {"name": "Fionn", "slug": "fionn", "sse": 116992.6039390564, "overlapYears": 29}, {"name": "Emerson", "slug": "emerson", "sse": 134802.24581282737, "overlapYears": 29}]}