{"name": "Said", "slug": "said", "sex": "boys", "minYears": 5, "neighbors": [{"name": "Reilly", "slug": "reilly", "sse": 8526.74679802917, "overlapYears": 29}, {"name": "Anwar", "slug": "anwar", "sse": 60773.69014775753, "overlapYears": 29}, {"name": "Ishmael", "slug": "ishmael", "sse": 80730.91133022308, "overlapYears": 29}, {"name": "Maurice", "slug": "maurice", "sse": 101597.56403923035, "overlapYears": 29}, {"name": "Edan", "slug": "edan", "sse": 102435.59359550476, "overlapYears": 29}, {"name": "Nick", "slug": "nick", "sse": 103024.76403999329, "overlapYears": 29}, {"name": "Zacharias", "slug": "zacharias", "sse": 106754.69162750244, "overlapYears": 29}, {"name": "Conall", "slug": "conall", "sse": 111877.02512359619, "overlapYears": 29}, {"name": "Jameel", "slug": "jameel", "sse": 120281.16305398941, "overlapYears": 29}, {"name": "Salim", "slug": "salim", "sse": 120699.28325119615, "overlapYears": 29}]}