{"name": "Salmaan", "slug": "salmaan", "sex": "boys", "minYears": 5, "neighbors": [{"name": "Hywel", "slug": "hywel", "sse": 14069.863655090332, "overlapYears": 29}, {"name": "Azhar", "slug": "azhar", "sse": 26145.222935676575, "overlapYears": 29}, {"name": "Yahye", "slug": "yahye", "sse": 40686.25640630722, "overlapYears": 29}, {"name": "Dhillon", "slug": "dhillon", "sse": 71242.0344645977, "overlapYears": 29}, {"name": "Pascal", "slug": "pascal", "sse": 88106.728910923, "overlapYears": 29}, {"name": "Ghulam", "slug": "ghulam", "sse": 92947.50278902054, "overlapYears": 29}, {"name": "Kori", "slug": "kori", "sse": 104166.88503932953, "overlapYears": 28}, {"name": "Umayr", "slug": "umayr", "sse": 129143.40312862396, "overlapYears": 29}, {"name": "Terrence", "slug": "terrence", "sse": 155990.8093150705, "overlapYears": 29}, {"name": "Neal", "slug": "neal", "sse": 208018.76358413696, "overlapYears": 28}]}