{"name": "Thierry", "slug": "thierry", "sex": "boys", "minYears": 5, "neighbors": [{"name": "Roland", "slug": "roland", "sse": 12422.349260985851, "overlapYears": 29}, {"name": "Khaled", "slug": "khaled", "sse": 15317.383743842132, "overlapYears": 29}, {"name": "Yisroel", "slug": "yisroel", "sse": 19023.8625613451, "overlapYears": 29}, {"name": "Quentin", "slug": "quentin", "sse": 23245.190147697926, "overlapYears": 29}, {"name": "Eduardo", "slug": "eduardo", "sse": 23935.36650264263, "overlapYears": 29}, {"name": "Mahmoud", "slug": "mahmoud", "sse": 37260.829556941986, "overlapYears": 29}, {"name": "Codie", "slug": "codie", "sse": 49544.33448266983, "overlapYears": 29}, {"name": "Manveer", "slug": "manveer", "sse": 69396.88719213009, "overlapYears": 29}, {"name": "Arnav", "slug": "arnav", "sse": 77330.18735599518, "overlapYears": 26}, {"name": "Dario", "slug": "dario", "sse": 85925.96995067596, "overlapYears": 29}]}