{"name": "Tiago", "slug": "tiago", "sex": "boys", "minYears": 5, "neighbors": [{"name": "Tommy-Lee", "slug": "tommy-lee", "sse": 2682.127586245537, "overlapYears": 29}, {"name": "Kyan", "slug": "kyan", "sse": 10606.108867019415, "overlapYears": 29}, {"name": "Ishaq", "slug": "ishaq", "sse": 12144.280295491219, "overlapYears": 29}, {"name": "Clark", "slug": "clark", "sse": 29152.893596172333, "overlapYears": 29}, {"name": "Sulayman", "slug": "sulayman", "sse": 64692.31083750725, "overlapYears": 29}, {"name": "Dawson", "slug": "dawson", "sse": 65608.32302165031, "overlapYears": 27}, {"name": "Herbie", "slug": "herbie", "sse": 94161.77635467052, "overlapYears": 29}, {"name": "Omer", "slug": "omer", "sse": 114034.97093582153, "overlapYears": 29}, {"name": "Taha", "slug": "taha", "sse": 116052.56403827667, "overlapYears": 29}, {"name": "Nikolas", "slug": "nikolas", "sse": 123156.03990149498, "overlapYears": 29}]}