{"name": "Zayd", "slug": "zayd", "sex": "boys", "minYears": 5, "neighbors": [{"name": "Cassius", "slug": "cassius", "sse": 35421.73448270559, "overlapYears": 29}, {"name": "Monty", "slug": "monty", "sse": 53923.62758684158, "overlapYears": 29}, {"name": "Remy", "slug": "remy", "sse": 57146.52167481184, "overlapYears": 29}, {"name": "Rafe", "slug": "rafe", "sse": 70736.490639925, "overlapYears": 29}, {"name": "Finnley", "slug": "finnley", "sse": 96559.66539955139, "overlapYears": 28}, {"name": "Abel", "slug": "abel", "sse": 111770.2729063034, "overlapYears": 29}, {"name": "Preston", "slug": "preston", "sse": 121358.46748767945, "overlapYears": 29}, {"name": "Yunus", "slug": "yunus", "sse": 129718.1211823225, "overlapYears": 29}, {"name": "Otto", "slug": "otto", "sse": 149978.90344829112, "overlapYears": 29}, {"name": "River", "slug": "river", "sse": 204435.46995067596, "overlapYears": 29}]}