{"name": "Chester", "sex": "boys", "ranks": [{"year": 1996, "rank": 654}, {"year": 1997, "rank": 554}, {"year": 1998, "rank": 629}, {"year": 1999, "rank": 603}, {"year": 2000, "rank": 691}, {"year": 2001, "rank": 814}, {"year": 2002, "rank": 907}, {"year": 2003, "rank": 833}, {"year": 2004, "rank": 1110}, {"year": 2005, "rank": 872}, {"year": 2006, "rank": 814}, {"year": 2007, "rank": 677}, {"year": 2008, "rank": 527}, {"year": 2009, "rank": 520}, {"year": 2010, "rank": 543}, {"year": 2011, "rank": 588}, {"year": 2012, "rank": 507}, {"year": 2013, "rank": 581}, {"year": 2014, "rank": 359}, {"year": 2015, "rank": 231}, {"year": 2016, "rank": 225}, {"year": 2017, "rank": 195}, {"year": 2018, "rank": 112}, {"year": 2019, "rank": 90}, {"year": 2020, "rank": 84}, {"year": 2021, "rank": 87}, {"year": 2022, "rank": 91}, {"year": 2023, "rank": 89}, {"year": 2024, "rank": 116}]}