{"name": "Danilo", "sex": "boys", "ranks": [{"year": 1996, "rank": 2863}, {"year": 1997, "rank": 2337}, {"year": 1998, "rank": 2901}, {"year": 2000, "rank": 3036}, {"year": 2001, "rank": 2587}, {"year": 2002, "rank": 2636}, {"year": 2003, "rank": 1513}, {"year": 2004, "rank": 2304}, {"year": 2006, "rank": 2870}, {"year": 2008, "rank": 2507}, {"year": 2009, "rank": 2837}, {"year": 2011, "rank": 3300}, {"year": 2012, "rank": 2458}, {"year": 2013, "rank": 2216}, {"year": 2015, "rank": 3004}, {"year": 2016, "rank": 3478}, {"year": 2017, "rank": 2512}, {"year": 2018, "rank": 4749}, {"year": 2019, "rank": 3013}, {"year": 2020, "rank": 3334}, {"year": 2021, "rank": 3451}, {"year": 2022, "rank": 2755}, {"year": 2023, "rank": 2546}, {"year": 2024, "rank": 5119}]}