{"name": "Mayson", "sex": "boys", "ranks": [{"year": 1996, "rank": 2357}, {"year": 1997, "rank": 2859}, {"year": 1998, "rank": 2419}, {"year": 1999, "rank": 2943}, {"year": 2000, "rank": 3036}, {"year": 2002, "rank": 2254}, {"year": 2003, "rank": 2189}, {"year": 2004, "rank": 1732}, {"year": 2005, "rank": 2174}, {"year": 2006, "rank": 1280}, {"year": 2007, "rank": 1440}, {"year": 2008, "rank": 1206}, {"year": 2009, "rank": 972}, {"year": 2010, "rank": 1109}, {"year": 2011, "rank": 929}, {"year": 2012, "rank": 927}, {"year": 2013, "rank": 804}, {"year": 2014, "rank": 1061}, {"year": 2015, "rank": 950}, {"year": 2016, "rank": 1022}, {"year": 2017, "rank": 1546}, {"year": 2018, "rank": 1533}, {"year": 2019, "rank": 1217}, {"year": 2020, "rank": 1548}, {"year": 2021, "rank": 1250}, {"year": 2022, "rank": 1366}, {"year": 2023, "rank": 2007}, {"year": 2024, "rank": 2263}]}