{"name": "Sully", "sex": "boys", "ranks": [{"year": 2005, "rank": 3208}, {"year": 2006, "rank": 4052}, {"year": 2011, "rank": 2613}, {"year": 2012, "rank": 4805}, {"year": 2013, "rank": 4685}, {"year": 2014, "rank": 2964}, {"year": 2015, "rank": 3373}, {"year": 2016, "rank": 3478}, {"year": 2017, "rank": 2052}, {"year": 2018, "rank": 2693}, {"year": 2019, "rank": 1869}, {"year": 2020, "rank": 1548}, {"year": 2021, "rank": 1078}, {"year": 2022, "rank": 993}, {"year": 2023, "rank": 719}, {"year": 2024, "rank": 509}]}